napari_psfgenerator/__init__.py
napari_psfgenerator/_reader.py
napari_psfgenerator/_sample_data.py
napari_psfgenerator/_widget.py
napari_psfgenerator/_writer.py
napari_psfgenerator/napari.yaml
napari_psfgenerator/_tests/__init__.py
napari_psfgenerator/_tests/test_reader.py
napari_psfgenerator/_tests/test_sample_data.py
napari_psfgenerator/_tests/test_widget.py
napari_psfgenerator/_tests/test_writer.py
napari_psfgenerator-0.4.1.dist-info/licenses/LICENSE
napari_psfgenerator-0.4.1.dist-info/METADATA
napari_psfgenerator-0.4.1.dist-info/WHEEL
napari_psfgenerator-0.4.1.dist-info/entry_points.txt
napari_psfgenerator-0.4.1.dist-info/top_level.txt
napari_psfgenerator-0.4.1.dist-info/RECORD
