Metadata-Version: 2.4
Name: napari-psfgenerator
Version: 0.4.1
Summary: Plugin to compute the focal electric field
Author-email: Vasiliki Stergiopoulou <vasiliki.stergiopoulou@epfl.ch>, Jonathan Dong <jonathan.dong@epfl.ch>, Yan Liu <yan.liu@epfl.ch>, Daniel Sage <daniel.sage@epfl.ch>
License: 
Project-URL: Bug Tracker, https://github.com/VStergiop/napari-psfgenerator/issues
Project-URL: Documentation, https://github.com/VStergiop/napari-psfgenerator#README.md
Project-URL: Source Code, https://github.com/VStergiop/napari-psfgenerator
Project-URL: User Support, https://github.com/VStergiop/napari-psfgenerator/issues
Classifier: Development Status :: 2 - Pre-Alpha
Classifier: Framework :: napari
Classifier: Intended Audience :: Developers
Classifier: License :: OSI Approved :: MIT License
Classifier: Operating System :: OS Independent
Classifier: Programming Language :: Python
Classifier: Programming Language :: Python :: 3
Classifier: Programming Language :: Python :: 3 :: Only
Classifier: Programming Language :: Python :: 3.9
Classifier: Programming Language :: Python :: 3.10
Classifier: Programming Language :: Python :: 3.11
Classifier: Programming Language :: Python :: 3.12
Classifier: Topic :: Scientific/Engineering :: Image Processing
Requires-Python: >=3.9
License-File: LICENSE
Requires-Dist: magicgui
Requires-Dist: qtpy
Requires-Dist: psf-generator
Requires-Dist: pyqt5
Requires-Dist: napari
Provides-Extra: napari
Requires-Dist: napari; extra == "napari"
Provides-Extra: testing
Requires-Dist: tox; extra == "testing"
Requires-Dist: pytest; extra == "testing"
Requires-Dist: pytest-cov; extra == "testing"
Requires-Dist: pytest-qt; extra == "testing"
Requires-Dist: napari; extra == "testing"
Requires-Dist: pyqt5; extra == "testing"
Dynamic: license-file
